lind/__init__.py
lind/_version.py
lind-0.0.14.dist-info/LICENSE.md
lind-0.0.14.dist-info/METADATA
lind-0.0.14.dist-info/WHEEL
lind-0.0.14.dist-info/top_level.txt
lind-0.0.14.dist-info/RECORD
