Metadata-Version: 2.1
Name: lind
Version: 0.0.14
Summary: Package for implementing bayesian deep conjugate models in python.
Home-page: UNKNOWN
Author: James Montgomery
Author-email: jamesoneillmontgomery@gmail.com
License: # License
Requires-Dist: numpy (==1.17.4)
Requires-Dist: scipy (==1.4.1)
Requires-Dist: pandas (==0.23.4)
Requires-Dist: scikit-learn (==0.21.3)
Requires-Dist: matplotlib (==3.0.3)
Provides-Extra: tests
Requires-Dist: pytest (==5.3.5) ; extra == 'tests'
Requires-Dist: pytest-cov (==2.8.1) ; extra == 'tests'
Requires-Dist: pytest-mock (==3.0.0) ; extra == 'tests'
Requires-Dist: pytest-lazy-fixture (==0.6.3) ; extra == 'tests'
Requires-Dist: pytest-xdist (==1.31.0) ; extra == 'tests'
Requires-Dist: pyyaml (==3.12) ; extra == 'tests'
Requires-Dist: pylint (==2.4.4) ; extra == 'tests'
